topssh/__init__.py
topssh/base.py
topssh/sftp.py
topssh/ssh.py
topssh/ssh_lite.py
topssh-2025.5.26.dist-info/licenses/LICENSE.txt
topssh-2025.5.26.dist-info/METADATA
topssh-2025.5.26.dist-info/WHEEL
topssh-2025.5.26.dist-info/top_level.txt
topssh-2025.5.26.dist-info/RECORD
