Metadata-Version: 2.4
Name: topssh
Version: 2025.5.26
Summary: a package on top of fabric to use SSH easily
Author-email: Lix Xu <xuzenglin@gmail.com>
License: BSD 3-Clause License
Project-URL: Homepage, https://github.com/lixxu/topssh
Project-URL: Bug Tracker, https://github.com/lixxu/topssh/issues
Keywords: ssh,fabric,paramiko
Classifier: Programming Language :: Python :: 3
Classifier: License :: OSI Approved :: BSD License
Classifier: Operating System :: OS Independent
Requires-Python: >=3.8
License-File: LICENSE.txt
Requires-Dist: fabric>=3.2.2
Requires-Dist: py-term>=0.7
Dynamic: license-file
